control/__init__.py
control/internet_connection.py
control/reboot_computer.py
control/zte.py
control/network/__init__.py
control/network/connection.py
control/network/ip.py
etc/buoy/ip.yaml
etc/buoy/logging.yaml
tests/control/__init__.py
tests/control/test_connection.py
tests/control/test_get_public_ip.py
tests/control/test_internet_connection.py
tests/control/test_public_ip.py
check_network-0.0.1.dist-info/METADATA
check_network-0.0.1.dist-info/WHEEL
check_network-0.0.1.dist-info/entry_points.txt
check_network-0.0.1.dist-info/top_level.txt
check_network-0.0.1.dist-info/RECORD
